app.py
src/__about__.py
src/get_commodities.py
src/get_token.py
src/process_data.py
src/region_locale.py
wow_commodities-1.1.1.dist-info/METADATA
wow_commodities-1.1.1.dist-info/WHEEL
wow_commodities-1.1.1.dist-info/entry_points.txt
wow_commodities-1.1.1.dist-info/licenses/LICENSE.txt
wow_commodities-1.1.1.dist-info/RECORD
