Metadata-Version: 2.4
Name: WoW_Commodities
Version: 1.1.1
Summary: Download World of Warcraft commodities auction data for the specified region.
Project-URL: Documentation, https://github.com/Godrigos/WoW_Commodities#readme
Project-URL: Issues, https://github.com/Godrigos/WoW_Commodities/issues
Project-URL: Source, https://github.com/Godrigos/WoW_Commodities
Author-email: "Aluizio, R." <gambit01@bol.com.br>
License-Expression: LGPL-3.0-or-later
License-File: LICENSE.txt
Keywords: Auction House,Commodities,World of Warcraft
Classifier: Development Status :: 5 - Production/Stable
Classifier: Operating System :: OS Independent
Classifier: Programming Language :: Python :: 3.11
Classifier: Topic :: Games/Entertainment
Requires-Python: >=3.10
Requires-Dist: pandas~=2.2
Requires-Dist: requests~=2.32
Requires-Dist: rich~=14.0
